CHANGELOG.txt
LICENSE.txt
MANIFEST.in
README.md
setup.py
global_hotkeys/__init__.py
global_hotkeys/hotkey_checker.py
global_hotkeys/keycode_checker.py
global_hotkeys/keycodes.py
global_hotkeys.egg-info/PKG-INFO
global_hotkeys.egg-info/SOURCES.txt
global_hotkeys.egg-info/dependency_links.txt
global_hotkeys.egg-info/requires.txt
global_hotkeys.egg-info/top_level.txt
tests/_t.py
tests/global_snippets.py
tests/test.py