Metadata-Version: 2.1
Name: global-hotkeys
Version: 0.1.7
Home-page: https://github.com/btsdev
Author: btsdev
Author-email: btsdevman@gmail.com
License: MIT
Keywords: hotkeys,shortcuts
Classifier: Development Status :: 4 - Beta
Classifier: Intended Audience :: Developers
Classifier: Operating System :: Microsoft :: Windows
Classifier: License :: OSI Approved :: MIT License
Classifier: Programming Language :: Python :: 3
Provides-Extra: dev
License-File: LICENSE.txt
